tree_sitter_languages/__init__.py
tree_sitter_languages/core.cpython-36m-aarch64-linux-gnu.so
tree_sitter_languages/languages.so
tree_sitter_languages_arm64-1.6.0.dist-info/METADATA
tree_sitter_languages_arm64-1.6.0.dist-info/LICENSE
tree_sitter_languages_arm64-1.6.0.dist-info/WHEEL
tree_sitter_languages_arm64-1.6.0.dist-info/top_level.txt
tree_sitter_languages_arm64-1.6.0.dist-info/RECORD
